rudalle/__init__.py
rudalle/image_prompts.py
rudalle/pipelines.py
rudalle/tokenizer.py
rudalle/utils.py
rudalle/dalle/__init__.py
rudalle/dalle/fp16.py
rudalle/dalle/image_attention.py
rudalle/dalle/model.py
rudalle/dalle/transformer.py
rudalle/dalle/utils.py
rudalle/emojich_unet/__init__.py
rudalle/realesrgan/__init__.py
rudalle/realesrgan/arch_util.py
rudalle/realesrgan/model.py
rudalle/realesrgan/rrdbnet_arch.py
rudalle/realesrgan/utils.py
rudalle/vae/__init__.py
rudalle/vae/decoder_dwt.py
rudalle/vae/model.py
rudalle/vae/pytorch_wavelets_utils.py
rudalle/vae/vqgan.gumbelf8-sber.config.yml
rudalle-1.1.3.dist-info/LICENSE.txt
rudalle-1.1.3.dist-info/METADATA
rudalle-1.1.3.dist-info/WHEEL
rudalle-1.1.3.dist-info/top_level.txt
rudalle-1.1.3.dist-info/RECORD
