Metadata-Version: 2.1
Name: rudalle
Version: 1.1.3
Summary: ruDALL-E generate images from texts in Russian language
Author: SberAI, SberDevices
Author-email: shonenkov@phystech.edu
License: UNKNOWN
Platform: UNKNOWN
License-File: LICENSE.txt
Requires-Dist: taming-transformers (==0.0.1)
Requires-Dist: more-itertools (~=8.12.0)
Requires-Dist: transformers (~=4.10.2)
Requires-Dist: youtokentome (~=1.0.6)
Requires-Dist: omegaconf (>=2.0.0)
Requires-Dist: einops (~=0.3.2)
Requires-Dist: PyWavelets (==1.1.1)
Requires-Dist: segmentation-models-pytorch (==0.1.3)
Requires-Dist: opencv-python (==4.5.4.60)
Requires-Dist: torch
Requires-Dist: torchvision
Requires-Dist: matplotlib
